{"request":{"ric":"CNDX.L","fromDate":"2018-01-01T00:00:00","toDate":"2018-12-31T23:59:59","fids":["_DATE_END","CLOSE_PRC","HIGH_1","OPEN_PRC","LOW_1"],"samples":"D","appendRecentData":"all"},"data":[{"_DATE_END":"2018-01-02","LOW_1":"354.85","CLOSE_PRC":"360.0","HIGH_1":"360.3","OPEN_PRC":"355.6"},{"_DATE_END":"2018-01-03","LOW_1":"361.6","CLOSE_PRC":"364.4","HIGH_1":"364.4","OPEN_PRC":"361.61"},{"_DATE_END":"2018-01-04","LOW_1":"365.35","CLOSE_PRC":"365.23","HIGH_1":"366.32","OPEN_PRC":"365.52"},{"_DATE_END":"2018-01-05","LOW_1":"366.46","CLOSE_PRC":"368.235","HIGH_1":"367.99","OPEN_PRC":"366.59"},{"_DATE_END":"2018-01-08","LOW_1":"368.88","CLOSE_PRC":"370.315","HIGH_1":"370.05","OPEN_PRC":"369.8"},{"_DATE_END":"2018-01-09","LOW_1":"369.72","CLOSE_PRC":"370.905","HIGH_1":"371.3","OPEN_PRC":"370.68"},{"_DATE_END":"2018-01-10","LOW_1":"368.3","CLOSE_PRC":"368.365","HIGH_1":"369.65","OPEN_PRC":"369.65"},{"_DATE_END":"2018-01-11","LOW_1":"369.89","CLOSE_PRC":"370.35","HIGH_1":"370.68","OPEN_PRC":"370.22"},{"_DATE_END":"2018-01-12","LOW_1":"371.84","CLOSE_PRC":"374.07","HIGH_1":"374.06","OPEN_PRC":"372.99"},{"_DATE_END":"2018-01-15","LOW_1":"375.31","CLOSE_PRC":"375.72","HIGH_1":"375.78","OPEN_PRC":"375.76"},{"_DATE_END":"2018-01-16","LOW_1":"376.59","CLOSE_PRC":"377.15","HIGH_1":"378.13","OPEN_PRC":"376.59"},{"_DATE_END":"2018-01-17","LOW_1":"374.61","CLOSE_PRC":"375.55","HIGH_1":"376.02","OPEN_PRC":"374.95"},{"_DATE_END":"2018-01-18","LOW_1":"377.07","CLOSE_PRC":"377.4","HIGH_1":"377.66","OPEN_PRC":"377.55"},{"_DATE_END":"2018-01-19","LOW_1":"377.28","CLOSE_PRC":"378.26","HIGH_1":"379.2","OPEN_PRC":"377.79"},{"_DATE_END":"2018-01-22","LOW_1":"378.73","CLOSE_PRC":"380.93","HIGH_1":"381.2","OPEN_PRC":"378.93"},{"_DATE_END":"2018-01-23","LOW_1":"383.62","CLOSE_PRC":"386.09","HIGH_1":"386.24","OPEN_PRC":"385.07"},{"_DATE_END":"2018-01-24","LOW_1":"385.13","CLOSE_PRC":"384.895","HIGH_1":"387.39","OPEN_PRC":"386.42"},{"_DATE_END":"2018-01-25","LOW_1":"384.01","CLOSE_PRC":"385.125","HIGH_1":"386.14","OPEN_PRC":"384.09"},{"_DATE_END":"2018-01-26","LOW_1":"385.27","CLOSE_PRC":"386.805","HIGH_1":"386.05","OPEN_PRC":"385.27"},{"_DATE_END":"2018-01-29","LOW_1":"387.56","CLOSE_PRC":"387.89","HIGH_1":"389.27","OPEN_PRC":"389.2"},{"_DATE_END":"2018-01-30","LOW_1":"382.61","CLOSE_PRC":"385.0","HIGH_1":"385.97","OPEN_PRC":"385.67"},{"_DATE_END":"2018-01-31","LOW_1":"385.44","CLOSE_PRC":"385.215","HIGH_1":"387.0","OPEN_PRC":"385.87"},{"_DATE_END":"2018-02-01","LOW_1":"384.13","CLOSE_PRC":"385.49","HIGH_1":"386.79","OPEN_PRC":"386.79"},{"_DATE_END":"2018-02-02","LOW_1":"379.07","CLOSE_PRC":"379.175","HIGH_1":"383.81","OPEN_PRC":"383.81"},{"_DATE_END":"2018-02-05","LOW_1":"370.83","CLOSE_PRC":"375.04","HIGH_1":"377.13","OPEN_PRC":"374.31"},{"_DATE_END":"2018-02-06","LOW_1":"352.8","CLOSE_PRC":"359.445","HIGH_1":"365.05","OPEN_PRC":"357.28"},{"_DATE_END":"2018-02-07","LOW_1":"365.51","CLOSE_PRC":"371.485","HIGH_1":"371.75","OPEN_PRC":"365.51"},{"_DATE_END":"2018-02-08","LOW_1":"358.57","CLOSE_PRC":"358.76","HIGH_1":"366.16","OPEN_PRC":"365.22"},{"_DATE_END":"2018-02-09","LOW_1":"350.4","CLOSE_PRC":"350.525","HIGH_1":"355.7","OPEN_PRC":"353.0"},{"_DATE_END":"2018-02-12","LOW_1":"356.76","CLOSE_PRC":"360.36","HIGH_1":"361.23","OPEN_PRC":"356.76"},{"_DATE_END":"2018-02-13","LOW_1":"359.43","CLOSE_PRC":"361.475","HIGH_1":"361.84","OPEN_PRC":"360.97"},{"_DATE_END":"2018-02-14","LOW_1":"358.3","CLOSE_PRC":"367.24","HIGH_1":"366.71","OPEN_PRC":"365.3"},{"_DATE_END":"2018-02-15","LOW_1":"370.6","CLOSE_PRC":"373.675","HIGH_1":"374.95","OPEN_PRC":"373.03"},{"_DATE_END":"2018-02-16","LOW_1":"377.18","CLOSE_PRC":"378.345","HIGH_1":"380.15","OPEN_PRC":"380.04"},{"_DATE_END":"2018-02-19","LOW_1":"376.27","CLOSE_PRC":"375.8","HIGH_1":"378.04","OPEN_PRC":"377.51"},{"_DATE_END":"2018-02-20","LOW_1":"373.17","CLOSE_PRC":"378.83","HIGH_1":"377.35","OPEN_PRC":"375.63"},{"_DATE_END":"2018-02-21","LOW_1":"376.4","CLOSE_PRC":"380.235","HIGH_1":"379.76","OPEN_PRC":"377.26"},{"_DATE_END":"2018-02-22","LOW_1":"374.65","CLOSE_PRC":"378.61","HIGH_1":"378.35","OPEN_PRC":"374.65"},{"_DATE_END":"2018-02-23","LOW_1":"377.43","CLOSE_PRC":"378.885","HIGH_1":"378.95","OPEN_PRC":"378.04"},{"_DATE_END":"2018-02-26","LOW_1":"383.76","CLOSE_PRC":"386.395","HIGH_1":"386.05","OPEN_PRC":"384.23"},{"_DATE_END":"2018-02-27","LOW_1":"385.68","CLOSE_PRC":"385.54","HIGH_1":"388.18","OPEN_PRC":"387.48"},{"_DATE_END":"2018-02-28","LOW_1":"383.62","CLOSE_PRC":"384.415","HIGH_1":"385.65","OPEN_PRC":"384.11"},{"_DATE_END":"2018-03-01","LOW_1":"378.17","CLOSE_PRC":"379.59","HIGH_1":"382.18","OPEN_PRC":"382.12"},{"_DATE_END":"2018-03-02","LOW_1":"370.86","CLOSE_PRC":"373.665","HIGH_1":"375.54","OPEN_PRC":"375.09"},{"_DATE_END":"2018-03-05","LOW_1":"374.65","CLOSE_PRC":"379.79","HIGH_1":"378.45","OPEN_PRC":"374.65"},{"_DATE_END":"2018-03-06","LOW_1":"382.52","CLOSE_PRC":"381.865","HIGH_1":"384.3","OPEN_PRC":"383.4"},{"_DATE_END":"2018-03-07","LOW_1":"379.9","CLOSE_PRC":"382.585","HIGH_1":"383.67","OPEN_PRC":"380.25"},{"_DATE_END":"2018-03-08","LOW_1":"385.2","CLOSE_PRC":"386.695","HIGH_1":"386.7","OPEN_PRC":"385.33"},{"_DATE_END":"2018-03-09","LOW_1":"386.57","CLOSE_PRC":"391.695","HIGH_1":"390.8","OPEN_PRC":"386.87"},{"_DATE_END":"2018-03-12","LOW_1":"395.24","CLOSE_PRC":"396.64","HIGH_1":"397.08","OPEN_PRC":"396.2"},{"_DATE_END":"2018-03-13","LOW_1":"393.3","CLOSE_PRC":"393.265","HIGH_1":"398.15","OPEN_PRC":"396.49"},{"_DATE_END":"2018-03-14","LOW_1":"390.56","CLOSE_PRC":"390.685","HIGH_1":"393.8","OPEN_PRC":"392.59"},{"_DATE_END":"2018-03-15","LOW_1":"390.55","CLOSE_PRC":"391.395","HIGH_1":"391.55","OPEN_PRC":"391.05"},{"_DATE_END":"2018-03-16","LOW_1":"390.72","CLOSE_PRC":"390.07","HIGH_1":"391.72","OPEN_PRC":"391.35"},{"_DATE_END":"2018-03-19","LOW_1":"379.49","CLOSE_PRC":"380.395","HIGH_1":"386.64","OPEN_PRC":"386.64"},{"_DATE_END":"2018-03-20","LOW_1":"380.6","CLOSE_PRC":"382.375","HIGH_1":"383.15","OPEN_PRC":"381.95"},{"_DATE_END":"2018-03-21","LOW_1":"381.35","CLOSE_PRC":"383.31","HIGH_1":"382.84","OPEN_PRC":"382.84"},{"_DATE_END":"2018-03-22","LOW_1":"373.32","CLOSE_PRC":"375.345","HIGH_1":"378.65","OPEN_PRC":"378.34"},{"_DATE_END":"2018-03-23","LOW_1":"366.95","CLOSE_PRC":"369.02","HIGH_1":"371.2","OPEN_PRC":"369.66"},{"_DATE_END":"2018-03-26","LOW_1":"363.81","CLOSE_PRC":"364.91","HIGH_1":"369.82","OPEN_PRC":"368.02"},{"_DATE_END":"2018-03-27","LOW_1":"373.94","CLOSE_PRC":"374.45","HIGH_1":"379.36","OPEN_PRC":"378.2"},{"_DATE_END":"2018-03-28","LOW_1":"357.83","CLOSE_PRC":"357.24","HIGH_1":"364.4","OPEN_PRC":"362.38"},{"_DATE_END":"2018-03-29","LOW_1":"358.27","CLOSE_PRC":"363.07","HIGH_1":"362.15","OPEN_PRC":"361.01"},{"_DATE_END":"2018-04-03","LOW_1":"352.3","CLOSE_PRC":"357.39","HIGH_1":"359.33","OPEN_PRC":"356.63"},{"_DATE_END":"2018-04-04","LOW_1":"349.89","CLOSE_PRC":"357.59","HIGH_1":"356.45","OPEN_PRC":"356.3"},{"_DATE_END":"2018-04-05","LOW_1":"366.46","CLOSE_PRC":"367.725","HIGH_1":"368.1","OPEN_PRC":"367.88"},{"_DATE_END":"2018-04-06","LOW_1":"361.5","CLOSE_PRC":"362.38","HIGH_1":"365.57","OPEN_PRC":"362.9"},{"_DATE_END":"2018-04-09","LOW_1":"360.02","CLOSE_PRC":"364.34","HIGH_1":"364.3","OPEN_PRC":"361.17"},{"_DATE_END":"2018-04-10","LOW_1":"363.93","CLOSE_PRC":"365.645","HIGH_1":"367.05","OPEN_PRC":"367.05"},{"_DATE_END":"2018-04-11","LOW_1":"363.46","CLOSE_PRC":"367.21","HIGH_1":"366.68","OPEN_PRC":"365.9"},{"_DATE_END":"2018-04-12","LOW_1":"365.8","CLOSE_PRC":"370.34","HIGH_1":"368.52","OPEN_PRC":"365.8"},{"_DATE_END":"2018-04-13","LOW_1":"368.78","CLOSE_PRC":"369.155","HIGH_1":"371.85","OPEN_PRC":"369.4"},{"_DATE_END":"2018-04-16","LOW_1":"368.65","CLOSE_PRC":"369.585","HIGH_1":"370.75","OPEN_PRC":"369.29"},{"_DATE_END":"2018-04-17","LOW_1":"373.2","CLOSE_PRC":"377.885","HIGH_1":"377.4","OPEN_PRC":"373.78"},{"_DATE_END":"2018-04-18","LOW_1":"378.8","CLOSE_PRC":"379.925","HIGH_1":"380.25","OPEN_PRC":"379.25"},{"_DATE_END":"2018-04-19","LOW_1":"376.85","CLOSE_PRC":"376.795","HIGH_1":"380.0","OPEN_PRC":"380.0"},{"_DATE_END":"2018-04-20","LOW_1":"372.9","CLOSE_PRC":"370.455","HIGH_1":"375.33","OPEN_PRC":"374.82"},{"_DATE_END":"2018-04-23","LOW_1":"370.99","CLOSE_PRC":"373.275","HIGH_1":"373.1","OPEN_PRC":"371.16"},{"_DATE_END":"2018-04-24","LOW_1":"365.0","CLOSE_PRC":"366.025","HIGH_1":"372.11","OPEN_PRC":"370.55"},{"_DATE_END":"2018-04-25","LOW_1":"357.95","CLOSE_PRC":"362.965","HIGH_1":"361.6","OPEN_PRC":"361.6"},{"_DATE_END":"2018-04-26","LOW_1":"364.6","CLOSE_PRC":"368.395","HIGH_1":"368.3","OPEN_PRC":"364.6"},{"_DATE_END":"2018-04-27","LOW_1":"368.7","CLOSE_PRC":"370.81","HIGH_1":"375.85","OPEN_PRC":"374.43"},{"_DATE_END":"2018-04-30","LOW_1":"371.7","CLOSE_PRC":"370.675","HIGH_1":"372.23","OPEN_PRC":"371.9"},{"_DATE_END":"2018-05-01","LOW_1":"366.2","CLOSE_PRC":"367.25","HIGH_1":"367.8","OPEN_PRC":"367.55"},{"_DATE_END":"2018-05-02","LOW_1":"371.05","CLOSE_PRC":"371.255","HIGH_1":"373.3","OPEN_PRC":"372.63"},{"_DATE_END":"2018-05-03","LOW_1":"364.2","CLOSE_PRC":"363.945","HIGH_1":"369.25","OPEN_PRC":"368.7"},{"_DATE_END":"2018-05-04","LOW_1":"368.1","CLOSE_PRC":"374.51","HIGH_1":"374.05","OPEN_PRC":"369.05"},{"_DATE_END":"2018-05-07","LOW_1":"-","CLOSE_PRC":"-","HIGH_1":"-","OPEN_PRC":"-"},{"_DATE_END":"2018-05-08","LOW_1":"377.58","CLOSE_PRC":"378.38","HIGH_1":"379.2","OPEN_PRC":"379.08"},{"_DATE_END":"2018-05-09","LOW_1":"378.75","CLOSE_PRC":"379.065","HIGH_1":"380.35","OPEN_PRC":"379.65"},{"_DATE_END":"2018-05-10","LOW_1":"383.25","CLOSE_PRC":"385.725","HIGH_1":"385.3","OPEN_PRC":"383.7"},{"_DATE_END":"2018-05-11","LOW_1":"385.7","CLOSE_PRC":"386.36","HIGH_1":"387.35","OPEN_PRC":"386.66"},{"_DATE_END":"2018-05-14","LOW_1":"387.15","CLOSE_PRC":"388.49","HIGH_1":"389.2","OPEN_PRC":"387.66"},{"_DATE_END":"2018-05-15","LOW_1":"382.05","CLOSE_PRC":"381.78","HIGH_1":"386.3","OPEN_PRC":"386.3"},{"_DATE_END":"2018-05-16","LOW_1":"382.8","CLOSE_PRC":"383.84","HIGH_1":"385.09","OPEN_PRC":"383.0"},{"_DATE_END":"2018-05-17","LOW_1":"383.9","CLOSE_PRC":"385.99","HIGH_1":"386.3","OPEN_PRC":"383.9"},{"_DATE_END":"2018-05-18","LOW_1":"381.95","CLOSE_PRC":"382.935","HIGH_1":"384.8","OPEN_PRC":"384.55"},{"_DATE_END":"2018-05-21","LOW_1":"384.57","CLOSE_PRC":"383.085","HIGH_1":"385.5","OPEN_PRC":"384.65"},{"_DATE_END":"2018-05-22","LOW_1":"384.2","CLOSE_PRC":"384.465","HIGH_1":"385.7","OPEN_PRC":"384.35"},{"_DATE_END":"2018-05-23","LOW_1":"379.95","CLOSE_PRC":"382.4","HIGH_1":"382.35","OPEN_PRC":"381.7"},{"_DATE_END":"2018-05-24","LOW_1":"384.35","CLOSE_PRC":"384.485","HIGH_1":"387.44","OPEN_PRC":"386.45"},{"_DATE_END":"2018-05-25","LOW_1":"386.1","CLOSE_PRC":"387.825","HIGH_1":"387.99","OPEN_PRC":"387.6"},{"_DATE_END":"2018-05-28","LOW_1":"-","CLOSE_PRC":"-","HIGH_1":"-","OPEN_PRC":"-"},{"_DATE_END":"2018-05-29","LOW_1":"384.05","CLOSE_PRC":"386.015","HIGH_1":"386.5","OPEN_PRC":"386.07"},{"_DATE_END":"2018-05-30","LOW_1":"386.2","CLOSE_PRC":"387.72","HIGH_1":"388.0","OPEN_PRC":"386.84"},{"_DATE_END":"2018-05-31","LOW_1":"387.5","CLOSE_PRC":"388.59","HIGH_1":"388.8","OPEN_PRC":"388.8"},{"_DATE_END":"2018-06-01","LOW_1":"389.1","CLOSE_PRC":"392.905","HIGH_1":"393.1","OPEN_PRC":"389.2"},{"_DATE_END":"2018-06-04","LOW_1":"394.85","CLOSE_PRC":"396.105","HIGH_1":"395.85","OPEN_PRC":"395.1"},{"_DATE_END":"2018-06-05","LOW_1":"396.97","CLOSE_PRC":"397.915","HIGH_1":"398.75","OPEN_PRC":"396.97"},{"_DATE_END":"2018-06-06","LOW_1":"397.5","CLOSE_PRC":"399.41","HIGH_1":"400.05","OPEN_PRC":"400.05"},{"_DATE_END":"2018-06-07","LOW_1":"397.46","CLOSE_PRC":"397.97","HIGH_1":"401.5","OPEN_PRC":"401.45"},{"_DATE_END":"2018-06-08","LOW_1":"394.2","CLOSE_PRC":"396.795","HIGH_1":"397.15","OPEN_PRC":"394.2"},{"_DATE_END":"2018-06-11","LOW_1":"397.15","CLOSE_PRC":"398.5","HIGH_1":"398.23","OPEN_PRC":"397.75"},{"_DATE_END":"2018-06-12","LOW_1":"398.2","CLOSE_PRC":"399.91","HIGH_1":"399.91","OPEN_PRC":"398.75"},{"_DATE_END":"2018-06-13","LOW_1":"401.0","CLOSE_PRC":"403.58","HIGH_1":"403.45","OPEN_PRC":"401.15"},{"_DATE_END":"2018-06-14","LOW_1":"399.55","CLOSE_PRC":"404.68","HIGH_1":"404.68","OPEN_PRC":"399.55"},{"_DATE_END":"2018-06-15","LOW_1":"401.7","CLOSE_PRC":"402.61","HIGH_1":"405.17","OPEN_PRC":"404.86"},{"_DATE_END":"2018-06-18","LOW_1":"399.9","CLOSE_PRC":"403.045","HIGH_1":"401.65","OPEN_PRC":"401.65"},{"_DATE_END":"2018-06-19","LOW_1":"397.42","CLOSE_PRC":"399.825","HIGH_1":"399.78","OPEN_PRC":"398.31"},{"_DATE_END":"2018-06-20","LOW_1":"402.9","CLOSE_PRC":"405.015","HIGH_1":"405.0","OPEN_PRC":"403.05"},{"_DATE_END":"2018-06-21","LOW_1":"401.35","CLOSE_PRC":"403.045","HIGH_1":"406.44","OPEN_PRC":"406.44"},{"_DATE_END":"2018-06-22","LOW_1":"399.48","CLOSE_PRC":"400.7","HIGH_1":"403.15","OPEN_PRC":"402.9"},{"_DATE_END":"2018-06-25","LOW_1":"392.46","CLOSE_PRC":"391.17","HIGH_1":"398.47","OPEN_PRC":"398.09"},{"_DATE_END":"2018-06-26","LOW_1":"391.6","CLOSE_PRC":"392.365","HIGH_1":"393.83","OPEN_PRC":"392.72"},{"_DATE_END":"2018-06-27","LOW_1":"389.55","CLOSE_PRC":"393.66","HIGH_1":"395.39","OPEN_PRC":"391.84"},{"_DATE_END":"2018-06-28","LOW_1":"387.25","CLOSE_PRC":"389.895","HIGH_1":"390.23","OPEN_PRC":"388.28"},{"_DATE_END":"2018-06-29","LOW_1":"392.92","CLOSE_PRC":"394.01","HIGH_1":"395.0","OPEN_PRC":"394.15"},{"_DATE_END":"2018-07-02","LOW_1":"387.91","CLOSE_PRC":"391.175","HIGH_1":"391.75","OPEN_PRC":"389.11"},{"_DATE_END":"2018-07-03","LOW_1":"393.39","CLOSE_PRC":"393.885","HIGH_1":"397.23","OPEN_PRC":"395.64"},{"_DATE_END":"2018-07-04","LOW_1":"389.98","CLOSE_PRC":"390.075","HIGH_1":"390.9","OPEN_PRC":"390.69"},{"_DATE_END":"2018-07-05","LOW_1":"390.08","CLOSE_PRC":"392.76","HIGH_1":"393.0","OPEN_PRC":"390.08"},{"_DATE_END":"2018-07-06","LOW_1":"394.31","CLOSE_PRC":"399.73","HIGH_1":"399.73","OPEN_PRC":"396.1"},{"_DATE_END":"2018-07-09","LOW_1":"401.8","CLOSE_PRC":"403.06","HIGH_1":"403.84","OPEN_PRC":"402.6"},{"_DATE_END":"2018-07-10","LOW_1":"404.85","CLOSE_PRC":"405.075","HIGH_1":"406.21","OPEN_PRC":"406.21"},{"_DATE_END":"2018-07-11","LOW_1":"400.5","CLOSE_PRC":"402.675","HIGH_1":"404.47","OPEN_PRC":"400.64"},{"_DATE_END":"2018-07-12","LOW_1":"404.02","CLOSE_PRC":"407.795","HIGH_1":"407.85","OPEN_PRC":"404.02"},{"_DATE_END":"2018-07-13","LOW_1":"409.79","CLOSE_PRC":"410.805","HIGH_1":"410.93","OPEN_PRC":"410.93"},{"_DATE_END":"2018-07-16","LOW_1":"409.83","CLOSE_PRC":"409.755","HIGH_1":"411.2","OPEN_PRC":"410.66"},{"_DATE_END":"2018-07-17","LOW_1":"405.3","CLOSE_PRC":"409.42","HIGH_1":"409.75","OPEN_PRC":"405.54"},{"_DATE_END":"2018-07-18","LOW_1":"409.81","CLOSE_PRC":"411.175","HIGH_1":"412.12","OPEN_PRC":"412.12"},{"_DATE_END":"2018-07-19","LOW_1":"408.94","CLOSE_PRC":"410.175","HIGH_1":"410.65","OPEN_PRC":"410.6"},{"_DATE_END":"2018-07-20","LOW_1":"408.75","CLOSE_PRC":"411.445","HIGH_1":"411.57","OPEN_PRC":"410.57"},{"_DATE_END":"2018-07-23","LOW_1":"406.75","CLOSE_PRC":"408.465","HIGH_1":"408.53","OPEN_PRC":"407.59"},{"_DATE_END":"2018-07-24","LOW_1":"412.25","CLOSE_PRC":"413.62","HIGH_1":"415.35","OPEN_PRC":"412.25"},{"_DATE_END":"2018-07-25","LOW_1":"411.6","CLOSE_PRC":"413.41","HIGH_1":"413.49","OPEN_PRC":"411.87"},{"_DATE_END":"2018-07-26","LOW_1":"411.37","CLOSE_PRC":"413.065","HIGH_1":"412.75","OPEN_PRC":"411.37"},{"_DATE_END":"2018-07-27","LOW_1":"409.48","CLOSE_PRC":"409.645","HIGH_1":"414.51","OPEN_PRC":"413.58"},{"_DATE_END":"2018-07-30","LOW_1":"400.56","CLOSE_PRC":"400.85","HIGH_1":"405.79","OPEN_PRC":"404.26"},{"_DATE_END":"2018-07-31","LOW_1":"400.15","CLOSE_PRC":"402.27","HIGH_1":"403.0","OPEN_PRC":"401.03"},{"_DATE_END":"2018-08-01","LOW_1":"403.24","CLOSE_PRC":"404.645","HIGH_1":"405.2","OPEN_PRC":"403.55"},{"_DATE_END":"2018-08-02","LOW_1":"401.39","CLOSE_PRC":"406.495","HIGH_1":"405.55","OPEN_PRC":"402.85"},{"_DATE_END":"2018-08-03","LOW_1":"410.16","CLOSE_PRC":"410.39","HIGH_1":"411.6","OPEN_PRC":"410.2"},{"_DATE_END":"2018-08-06","LOW_1":"411.09","CLOSE_PRC":"412.22","HIGH_1":"412.22","OPEN_PRC":"411.83"},{"_DATE_END":"2018-08-07","LOW_1":"414.39","CLOSE_PRC":"414.325","HIGH_1":"415.8","OPEN_PRC":"414.8"},{"_DATE_END":"2018-08-08","LOW_1":"414.18","CLOSE_PRC":"416.08","HIGH_1":"416.24","OPEN_PRC":"415.25"},{"_DATE_END":"2018-08-09","LOW_1":"415.14","CLOSE_PRC":"416.48","HIGH_1":"416.8","OPEN_PRC":"415.34"},{"_DATE_END":"2018-08-10","LOW_1":"412.5","CLOSE_PRC":"413.2","HIGH_1":"413.78","OPEN_PRC":"413.03"},{"_DATE_END":"2018-08-13","LOW_1":"410.62","CLOSE_PRC":"413.165","HIGH_1":"415.2","OPEN_PRC":"411.22"},{"_DATE_END":"2018-08-14","LOW_1":"411.66","CLOSE_PRC":"413.965","HIGH_1":"414.82","OPEN_PRC":"414.27"},{"_DATE_END":"2018-08-15","LOW_1":"407.25","CLOSE_PRC":"408.23","HIGH_1":"414.6","OPEN_PRC":"414.35"},{"_DATE_END":"2018-08-16","LOW_1":"411.68","CLOSE_PRC":"412.905","HIGH_1":"412.81","OPEN_PRC":"411.68"},{"_DATE_END":"2018-08-17","LOW_1":"407.36","CLOSE_PRC":"408.835","HIGH_1":"411.17","OPEN_PRC":"410.58"},{"_DATE_END":"2018-08-20","LOW_1":"409.11","CLOSE_PRC":"409.635","HIGH_1":"412.25","OPEN_PRC":"412.15"},{"_DATE_END":"2018-08-21","LOW_1":"410.8","CLOSE_PRC":"412.47","HIGH_1":"413.15","OPEN_PRC":"410.8"},{"_DATE_END":"2018-08-22","LOW_1":"410.45","CLOSE_PRC":"413.45","HIGH_1":"413.45","OPEN_PRC":"410.65"},{"_DATE_END":"2018-08-23","LOW_1":"413.0","CLOSE_PRC":"413.065","HIGH_1":"415.74","OPEN_PRC":"413.45"},{"_DATE_END":"2018-08-24","LOW_1":"413.82","CLOSE_PRC":"416.41","HIGH_1":"416.76","OPEN_PRC":"413.88"},{"_DATE_END":"2018-08-27","LOW_1":"-","CLOSE_PRC":"-","HIGH_1":"-","OPEN_PRC":"-"},{"_DATE_END":"2018-08-28","LOW_1":"421.5","CLOSE_PRC":"421.815","HIGH_1":"422.44","OPEN_PRC":"421.5"},{"_DATE_END":"2018-08-29","LOW_1":"422.0","CLOSE_PRC":"425.69","HIGH_1":"425.02","OPEN_PRC":"422.5"},{"_DATE_END":"2018-08-30","LOW_1":"425.7","CLOSE_PRC":"426.23","HIGH_1":"427.2","OPEN_PRC":"425.7"},{"_DATE_END":"2018-08-31","LOW_1":"424.94","CLOSE_PRC":"426.09","HIGH_1":"427.3","OPEN_PRC":"425.94"},{"_DATE_END":"2018-09-03","LOW_1":"426.41","CLOSE_PRC":"427.205","HIGH_1":"427.24","OPEN_PRC":"426.5"},{"_DATE_END":"2018-09-04","LOW_1":"422.5","CLOSE_PRC":"424.96","HIGH_1":"427.67","OPEN_PRC":"427.67"},{"_DATE_END":"2018-09-05","LOW_1":"418.3","CLOSE_PRC":"417.885","HIGH_1":"424.12","OPEN_PRC":"423.25"},{"_DATE_END":"2018-09-06","LOW_1":"413.85","CLOSE_PRC":"414.225","HIGH_1":"419.74","OPEN_PRC":"418.6"},{"_DATE_END":"2018-09-07","LOW_1":"411.85","CLOSE_PRC":"416.43","HIGH_1":"416.8","OPEN_PRC":"415.11"},{"_DATE_END":"2018-09-10","LOW_1":"413.6","CLOSE_PRC":"415.015","HIGH_1":"416.34","OPEN_PRC":"415.19"},{"_DATE_END":"2018-09-11","LOW_1":"412.42","CLOSE_PRC":"416.22","HIGH_1":"416.36","OPEN_PRC":"416.36"},{"_DATE_END":"2018-09-12","LOW_1":"414.23","CLOSE_PRC":"416.775","HIGH_1":"419.3","OPEN_PRC":"419.3"},{"_DATE_END":"2018-09-13","LOW_1":"416.66","CLOSE_PRC":"420.985","HIGH_1":"420.95","OPEN_PRC":"416.66"},{"_DATE_END":"2018-09-14","LOW_1":"420.75","CLOSE_PRC":"421.2","HIGH_1":"423.03","OPEN_PRC":"422.77"},{"_DATE_END":"2018-09-17","LOW_1":"415.35","CLOSE_PRC":"416.11","HIGH_1":"419.4","OPEN_PRC":"419.2"},{"_DATE_END":"2018-09-18","LOW_1":"414.91","CLOSE_PRC":"419.04","HIGH_1":"419.1","OPEN_PRC":"414.91"},{"_DATE_END":"2018-09-19","LOW_1":"415.25","CLOSE_PRC":"416.2","HIGH_1":"417.62","OPEN_PRC":"417.62"},{"_DATE_END":"2018-09-20","LOW_1":"417.2","CLOSE_PRC":"421.355","HIGH_1":"421.5","OPEN_PRC":"417.29"},{"_DATE_END":"2018-09-21","LOW_1":"420.95","CLOSE_PRC":"421.68","HIGH_1":"423.3","OPEN_PRC":"423.28"},{"_DATE_END":"2018-09-24","LOW_1":"415.19","CLOSE_PRC":"419.57","HIGH_1":"419.32","OPEN_PRC":"417.0"},{"_DATE_END":"2018-09-25","LOW_1":"419.29","CLOSE_PRC":"420.8","HIGH_1":"421.62","OPEN_PRC":"420.7"},{"_DATE_END":"2018-09-26","LOW_1":"422.31","CLOSE_PRC":"423.96","HIGH_1":"423.93","OPEN_PRC":"422.9"},{"_DATE_END":"2018-09-27","LOW_1":"421.38","CLOSE_PRC":"425.57","HIGH_1":"426.18","OPEN_PRC":"421.61"},{"_DATE_END":"2018-09-28","LOW_1":"423.44","CLOSE_PRC":"425.425","HIGH_1":"425.45","OPEN_PRC":"424.72"},{"_DATE_END":"2018-10-01","LOW_1":"427.01","CLOSE_PRC":"428.32","HIGH_1":"428.42","OPEN_PRC":"427.69"},{"_DATE_END":"2018-10-02","LOW_1":"424.0","CLOSE_PRC":"427.135","HIGH_1":"427.05","OPEN_PRC":"424.4"},{"_DATE_END":"2018-10-03","LOW_1":"425.67","CLOSE_PRC":"426.59","HIGH_1":"427.3","OPEN_PRC":"425.84"},{"_DATE_END":"2018-10-04","LOW_1":"418.19","CLOSE_PRC":"418.19","HIGH_1":"423.49","OPEN_PRC":"423.43"},{"_DATE_END":"2018-10-05","LOW_1":"412.74","CLOSE_PRC":"412.3","HIGH_1":"418.3","OPEN_PRC":"417.32"},{"_DATE_END":"2018-10-08","LOW_1":"409.01","CLOSE_PRC":"408.985","HIGH_1":"413.05","OPEN_PRC":"412.13"},{"_DATE_END":"2018-10-09","LOW_1":"407.54","CLOSE_PRC":"412.78","HIGH_1":"413.66","OPEN_PRC":"410.12"},{"_DATE_END":"2018-10-10","LOW_1":"401.14","CLOSE_PRC":"401.695","HIGH_1":"411.35","OPEN_PRC":"411.2"},{"_DATE_END":"2018-10-11","LOW_1":"386.0","CLOSE_PRC":"390.655","HIGH_1":"394.0","OPEN_PRC":"389.6"},{"_DATE_END":"2018-10-12","LOW_1":"395.07","CLOSE_PRC":"396.595","HIGH_1":"398.31","OPEN_PRC":"397.45"},{"_DATE_END":"2018-10-15","LOW_1":"392.87","CLOSE_PRC":"397.5","HIGH_1":"398.14","OPEN_PRC":"396.2"},{"_DATE_END":"2018-10-16","LOW_1":"395.04","CLOSE_PRC":"401.435","HIGH_1":"401.09","OPEN_PRC":"395.04"},{"_DATE_END":"2018-10-17","LOW_1":"402.45","CLOSE_PRC":"404.11","HIGH_1":"409.4","OPEN_PRC":"409.4"},{"_DATE_END":"2018-10-18","LOW_1":"399.3","CLOSE_PRC":"399.48","HIGH_1":"405.9","OPEN_PRC":"404.6"},{"_DATE_END":"2018-10-19","LOW_1":"398.2","CLOSE_PRC":"399.33","HIGH_1":"402.35","OPEN_PRC":"399.14"},{"_DATE_END":"2018-10-22","LOW_1":"394.82","CLOSE_PRC":"399.455","HIGH_1":"400.39","OPEN_PRC":"397.07"},{"_DATE_END":"2018-10-23","LOW_1":"387.0","CLOSE_PRC":"390.495","HIGH_1":"392.33","OPEN_PRC":"392.33"},{"_DATE_END":"2018-10-24","LOW_1":"388.9","CLOSE_PRC":"389.0","HIGH_1":"397.33","OPEN_PRC":"394.27"},{"_DATE_END":"2018-10-25","LOW_1":"381.17","CLOSE_PRC":"389.245","HIGH_1":"389.2","OPEN_PRC":"382.16"},{"_DATE_END":"2018-10-26","LOW_1":"375.7","CLOSE_PRC":"380.83","HIGH_1":"382.1","OPEN_PRC":"382.1"},{"_DATE_END":"2018-10-29","LOW_1":"378.6","CLOSE_PRC":"378.34","HIGH_1":"388.35","OPEN_PRC":"383.91"},{"_DATE_END":"2018-10-30","LOW_1":"371.6","CLOSE_PRC":"376.755","HIGH_1":"377.6","OPEN_PRC":"377.22"},{"_DATE_END":"2018-10-31","LOW_1":"382.38","CLOSE_PRC":"387.815","HIGH_1":"390.55","OPEN_PRC":"382.43"},{"_DATE_END":"2018-11-01","LOW_1":"386.63","CLOSE_PRC":"391.03","HIGH_1":"391.41","OPEN_PRC":"387.64"},{"_DATE_END":"2018-11-02","LOW_1":"387.2","CLOSE_PRC":"388.14","HIGH_1":"396.26","OPEN_PRC":"395.53"},{"_DATE_END":"2018-11-05","LOW_1":"382.78","CLOSE_PRC":"383.53","HIGH_1":"389.21","OPEN_PRC":"388.09"},{"_DATE_END":"2018-11-06","LOW_1":"385.21","CLOSE_PRC":"387.98","HIGH_1":"390.69","OPEN_PRC":"386.4"},{"_DATE_END":"2018-11-07","LOW_1":"393.43","CLOSE_PRC":"397.72","HIGH_1":"398.41","OPEN_PRC":"394.0"},{"_DATE_END":"2018-11-08","LOW_1":"399.0","CLOSE_PRC":"399.655","HIGH_1":"401.0","OPEN_PRC":"401.0"},{"_DATE_END":"2018-11-09","LOW_1":"392.0","CLOSE_PRC":"392.51","HIGH_1":"396.85","OPEN_PRC":"396.85"},{"_DATE_END":"2018-11-12","LOW_1":"382.49","CLOSE_PRC":"380.42","HIGH_1":"393.03","OPEN_PRC":"393.03"},{"_DATE_END":"2018-11-13","LOW_1":"381.3","CLOSE_PRC":"385.7","HIGH_1":"386.55","OPEN_PRC":"383.43"},{"_DATE_END":"2018-11-14","LOW_1":"377.62","CLOSE_PRC":"379.045","HIGH_1":"385.42","OPEN_PRC":"380.21"},{"_DATE_END":"2018-11-15","LOW_1":"375.0","CLOSE_PRC":"378.78","HIGH_1":"380.5","OPEN_PRC":"380.42"},{"_DATE_END":"2018-11-16","LOW_1":"379.66","CLOSE_PRC":"381.83","HIGH_1":"383.85","OPEN_PRC":"382.17"},{"_DATE_END":"2018-11-19","LOW_1":"375.18","CLOSE_PRC":"374.475","HIGH_1":"385.75","OPEN_PRC":"383.79"},{"_DATE_END":"2018-11-20","LOW_1":"361.45","CLOSE_PRC":"365.75","HIGH_1":"369.15","OPEN_PRC":"368.94"},{"_DATE_END":"2018-11-21","LOW_1":"365.81","CLOSE_PRC":"369.53","HIGH_1":"369.75","OPEN_PRC":"366.54"},{"_DATE_END":"2018-11-22","LOW_1":"362.5","CLOSE_PRC":"363.255","HIGH_1":"365.7","OPEN_PRC":"365.7"},{"_DATE_END":"2018-11-23","LOW_1":"364.4","CLOSE_PRC":"365.66","HIGH_1":"367.55","OPEN_PRC":"364.8"},{"_DATE_END":"2018-11-26","LOW_1":"369.18","CLOSE_PRC":"370.24","HIGH_1":"370.5","OPEN_PRC":"370.5"},{"_DATE_END":"2018-11-27","LOW_1":"369.0","CLOSE_PRC":"373.27","HIGH_1":"373.89","OPEN_PRC":"371.0"},{"_DATE_END":"2018-11-28","LOW_1":"374.17","CLOSE_PRC":"374.82","HIGH_1":"376.35","OPEN_PRC":"374.29"},{"_DATE_END":"2018-11-29","LOW_1":"381.85","CLOSE_PRC":"383.155","HIGH_1":"384.46","OPEN_PRC":"384.38"},{"_DATE_END":"2018-11-30","LOW_1":"383.25","CLOSE_PRC":"384.49","HIGH_1":"386.2","OPEN_PRC":"384.89"},{"_DATE_END":"2018-12-03","LOW_1":"392.75","CLOSE_PRC":"393.39","HIGH_1":"397.43","OPEN_PRC":"397.3"},{"_DATE_END":"2018-12-04","LOW_1":"390.05","CLOSE_PRC":"390.62","HIGH_1":"392.34","OPEN_PRC":"390.85"},{"_DATE_END":"2018-12-05","LOW_1":"380.01","CLOSE_PRC":"380.57","HIGH_1":"382.05","OPEN_PRC":"381.3"},{"_DATE_END":"2018-12-06","LOW_1":"370.25","CLOSE_PRC":"370.245","HIGH_1":"374.85","OPEN_PRC":"374.85"},{"_DATE_END":"2018-12-07","LOW_1":"373.3","CLOSE_PRC":"373.615","HIGH_1":"381.0","OPEN_PRC":"377.46"},{"_DATE_END":"2018-12-10","LOW_1":"365.25","CLOSE_PRC":"366.3","HIGH_1":"371.75","OPEN_PRC":"368.19"},{"_DATE_END":"2018-12-11","LOW_1":"372.27","CLOSE_PRC":"375.08","HIGH_1":"379.3","OPEN_PRC":"372.27"},{"_DATE_END":"2018-12-12","LOW_1":"375.96","CLOSE_PRC":"381.955","HIGH_1":"382.42","OPEN_PRC":"375.96"},{"_DATE_END":"2018-12-13","LOW_1":"377.0","CLOSE_PRC":"377.51","HIGH_1":"380.9","OPEN_PRC":"380.74"},{"_DATE_END":"2018-12-14","LOW_1":"371.76","CLOSE_PRC":"372.53","HIGH_1":"374.03","OPEN_PRC":"373.0"},{"_DATE_END":"2018-12-17","LOW_1":"364.3","CLOSE_PRC":"367.78","HIGH_1":"368.95","OPEN_PRC":"368.23"},{"_DATE_END":"2018-12-18","LOW_1":"361.11","CLOSE_PRC":"362.36","HIGH_1":"363.9","OPEN_PRC":"361.61"},{"_DATE_END":"2018-12-19","LOW_1":"361.49","CLOSE_PRC":"364.1","HIGH_1":"365.5","OPEN_PRC":"362.31"},{"_DATE_END":"2018-12-20","LOW_1":"349.44","CLOSE_PRC":"349.375","HIGH_1":"355.8","OPEN_PRC":"351.59"},{"_DATE_END":"2018-12-21","LOW_1":"345.0","CLOSE_PRC":"346.77","HIGH_1":"351.56","OPEN_PRC":"351.01"},{"_DATE_END":"2018-12-24","LOW_1":"335.51","CLOSE_PRC":"335.81","HIGH_1":"340.37","OPEN_PRC":"339.84"},{"_DATE_END":"2018-12-27","LOW_1":"340.0","CLOSE_PRC":"343.36","HIGH_1":"348.3","OPEN_PRC":"348.06"},{"_DATE_END":"2018-12-28","LOW_1":"348.81","CLOSE_PRC":"350.84","HIGH_1":"353.25","OPEN_PRC":"351.72"},{"_DATE_END":"2018-12-31","LOW_1":"353.35","CLOSE_PRC":"354.33","HIGH_1":"354.55","OPEN_PRC":"354.52"}],"status":"OK","metadata":{"h._DATE_END":{"type":"date"},"h.CLOSE_PRC":{"type":"float.price"},"h.HIGH_1":{"type":"float.price"},"h.OPEN_PRC":{"type":"float.price"},"h.LOW_1":{"type":"float.price"}}}